{
  "10.60.170.215": {
    "belt": {
      "points": [
        [
          284,
          1124
        ],
        [
          437,
          515
        ],
        [
          660,
          537
        ],
        [
          611,
          1173
        ]
      ],
      "resolution": [
        1080,
        1920
      ]
    },
    "mask": {
      "points": [
        [
          435,
          251
        ],
        [
          142,
          868
        ],
        [
          562,
          917
        ],
        [
          684,
          217
        ]
      ],
      "resolution": [
        1080,
        1920
      ]
    }
  },
  "10.60.170.216": {
    "belt": {
      "points": [
        [
          268,
          1786
        ],
        [
          291,
          857
        ],
        [
          342,
          440
        ],
        [
          395,
          82
        ],
        [
          468,
          82
        ],
        [
          502,
          348
        ],
        [
          531,
          788
        ],
        [
          602,
          1771
        ]
      ],
      "resolution": [
        1080,
        1920
      ]
    },
    "mask": {
      "points": [
        [
          708,
          635
        ],
        [
          1071,
          666
        ],
        [
          1071,
          1124
        ],
        [
          786,
          1106
        ]
      ],
      "resolution": [
        1080,
        1920
      ]
    }
  }
}